{"P13": {"label": "bug", "labelColor": "#d73a4a", "postTitle": "\u6d4b\u8bd5  9", "postUrl": "post/ce-shi-%20%209.html", "commentNum": 0, "createdDate": "2024-01-07", "dateLabelColor": "#bc4c00"}, "P12": {"label": "bug", "labelColor": "#d73a4a", "postTitle": "\u6d4b\u8bd58", "postUrl": "post/ce-shi-8.html", "commentNum": 0, "createdDate": "2024-01-07", "dateLabelColor": "#bc4c00"}, "P11": {"label": "bug", "labelColor": "#d73a4a", "postTitle": "\u6d4b\u8bd57", "postUrl": "post/ce-shi-7.html", "commentNum": 0, "createdDate": "2024-01-07", "dateLabelColor": "#bc4c00"}, "P10": {"label": "bug", "labelColor": "#d73a4a", "postTitle": "\u6d4b\u8bd56", "postUrl": "post/ce-shi-6.html", "commentNum": 0, "createdDate": "2024-01-06", "dateLabelColor": "#bc4c00"}, "P9": {"label": "bug", "labelColor": "#d73a4a", "postTitle": "\u6d4b\u8bd55", "postUrl": "post/ce-shi-5.html", "commentNum": 0, "createdDate": "2024-01-06", "dateLabelColor": "#bc4c00"}, "P8": {"label": "bug", "labelColor": "#d73a4a", "postTitle": "\u6d4b\u8bd54", "postUrl": "post/ce-shi-4.html", "commentNum": 0, "createdDate": "2024-01-06", "dateLabelColor": "#bc4c00"}, "P7": {"label": "bug", "labelColor": "#d73a4a", "postTitle": "\u6d4b\u8bd53", "postUrl": "post/ce-shi-3.html", "commentNum": 0, "createdDate": "2024-01-06", "dateLabelColor": "#bc4c00"}, "P6": {"label": "bug", "labelColor": "#d73a4a", "postTitle": "\u6d4b\u8bd52", "postUrl": "post/ce-shi-2.html", "commentNum": 0, "createdDate": "2024-01-06", "dateLabelColor": "#bc4c00"}, "P5": {"label": "bug", "labelColor": "#d73a4a", "postTitle": "\u6d4b\u8bd51", "postUrl": "post/ce-shi-1.html", "commentNum": 0, "createdDate": "2024-01-06", "dateLabelColor": "#bc4c00"}, "P4": {"label": "bug", "labelColor": "#d73a4a", "postTitle": "\u6d4b\u8bd5bug\u6807\u7b7e", "postUrl": "post/ce-shi-bug-biao-qian.html", "commentNum": 0, "createdDate": "2024-01-06", "dateLabelColor": "#bc4c00"}, "P3": {"label": "bug", "labelColor": "#d73a4a", "postTitle": "\u6d4b\u8bd5md", "postUrl": "post/ce-shi-md.html", "commentNum": 0, "createdDate": "2024-01-06", "dateLabelColor": "#bc4c00"}, "P2": {"label": "duplicate", "labelColor": "#cfd3d7", "postTitle": "\u6d4b\u8bd5\u641c\u7d22", "postUrl": "post/ce-shi-sou-suo.html", "commentNum": 0, "createdDate": "2024-01-05", "dateLabelColor": "#bc4c00"}, "P1": {"label": "documentation", "labelColor": "#0075ca", "postTitle": "\u6d4b\u8bd5", "postUrl": "post/ce-shi.html", "commentNum": 0, "createdDate": "2024-01-05", "dateLabelColor": "#bc4c00"}}